aiven/__init__.py
aiven/client/__init__.py
aiven/client/__main__.py
aiven/client/_typing.py
aiven/client/argx.py
aiven/client/cli.py
aiven/client/cliarg.py
aiven/client/client.py
aiven/client/common.py
aiven/client/envdefault.py
aiven/client/pretty.py
aiven/client/py.typed
aiven/client/session.py
aiven/client/speller.py
aiven/client/units.py
aiven/client/version.py
aiven/client/connection_info/__init__.py
aiven/client/connection_info/_utils.py
aiven/client/connection_info/common.py
aiven/client/connection_info/kafka.py
aiven/client/connection_info/pg.py
aiven/client/connection_info/valkey.py
aiven_client-4.11.1.dist-info/METADATA
aiven_client-4.11.1.dist-info/WHEEL
aiven_client-4.11.1.dist-info/entry_points.txt
aiven_client-4.11.1.dist-info/licenses/LICENSE
aiven_client-4.11.1.dist-info/RECORD
