Metadata-Version: 2.4
Name: aiven-client
Version: 4.11.1
Summary: Aiven.io client library / command-line client
Project-URL: Homepage, https://github.com/aiven/aiven-client
Project-URL: Bug Tracker, https://github.com/aiven/aiven-client/issues
Project-URL: Documentation, https://docs.aiven.io/docs/tools/cli
Author-email: Aiven <support@aiven.io>
License: Apache License 2.0
License-File: LICENSE
Classifier: Development Status :: 5 - Production/Stable
Classifier: Intended Audience :: Developers
Classifier: License :: OSI Approved :: Apache Software License
Classifier: Programming Language :: Python :: 3.9
Classifier: Programming Language :: Python :: 3.10
Classifier: Programming Language :: Python :: 3.11
Classifier: Programming Language :: Python :: 3.12
Classifier: Programming Language :: Python :: 3.13
Classifier: Programming Language :: Python :: 3.14
Classifier: Topic :: Software Development :: Libraries
Requires-Python: >=3.9
Requires-Dist: certifi>=2015.11.20.1
Requires-Dist: requests-toolbelt>=0.9.0
Requires-Dist: requests>=2.2.1; sys_platform == 'linux'
Requires-Dist: requests>=2.9.1; sys_platform != 'linux'
Provides-Extra: dev
Requires-Dist: black>=24.4.2; extra == 'dev'
Requires-Dist: click; extra == 'dev'
Requires-Dist: flake8; extra == 'dev'
Requires-Dist: isort<7.0,>=6.1.0; extra == 'dev'
Requires-Dist: mypy<2.0,>=1.17.1; extra == 'dev'
Requires-Dist: pytest; extra == 'dev'
Requires-Dist: ruff; extra == 'dev'
Requires-Dist: types-requests<3.0,>=2.26.1; extra == 'dev'
